ngguy/__init__.py
ngguy/ngguy.py
ngguy-1.0.0.dist-info/METADATA
ngguy-1.0.0.dist-info/WHEEL
ngguy-1.0.0.dist-info/licenses/LICENSE
ngguy-1.0.0.dist-info/RECORD
