Metadata-Version: 2.4
Name: ngguy
Version: 1.0.0
Summary: A small but useful utility
Author-email: Paul Kreutzer <paulmkreutzer@icloud.com>
License-Expression: MIT
License-File: LICENSE
Classifier: Operating System :: OS Independent
Classifier: Programming Language :: Python :: 3
Requires-Python: >=3.13
